sanic_wtf-0.7.0.dist-info/METADATA
sanic_wtf-0.7.0.dist-info/WHEEL
sanic_wtf-0.7.0.dist-info/licenses/AUTHORS
sanic_wtf-0.7.0.dist-info/licenses/LICENSE
sanic_wtf/__init__.py
sanic_wtf-0.7.0.dist-info/RECORD
