Metadata-Version: 2.1
Name: Sanic-WTF
Version: 0.7.0
Summary: Sanic-WTF - Sanic meets WTForms
Author-Email: Philip Xu <pyx@xrefactor.com>
License: BSD-New
Classifier: Development Status :: 4 - Beta
Classifier: Environment :: Web Environment
Classifier: Intended Audience :: Developers
Classifier: License :: OSI Approved :: BSD License
Classifier: Operating System :: OS Independent
Classifier: Programming Language :: Python :: 3
Classifier: Topic :: Internet :: WWW/HTTP :: Dynamic Content
Classifier: Topic :: Software Development :: Libraries :: Python Modules
Project-URL: Homepage, https://github.com/pyx/sanic-wtf/
Requires-Python: >=3.7
Requires-Dist: sanic>=21.3.0
Requires-Dist: wtforms>=3.0.1
Requires-Dist: Sphinx; extra == "doc"
Requires-Dist: flake8; extra == "lint"
Requires-Dist: sanic-testing; extra == "test"
Requires-Dist: pytest-cov; extra == "test"
Provides-Extra: doc
Provides-Extra: lint
Provides-Extra: test
